<?xml version="1.0" encoding="UTF-8"?>
<!DOCTYPE mapper PUBLIC "-//mybatis.org//DTD Mapper 3.0//EN" "http://mybatis.org/dtd/mybatis-3-mapper.dtd">
<mapper namespace="com.dl.movieservice.dao.GroupsTopicMapper">
  <resultMap id="BaseResultMap" type="com.dl.movieservice.model.GroupsTopic">
    <id column="id" jdbcType="INTEGER" property="id" />
    <result column="title" jdbcType="VARCHAR" property="title" />
    <result column="user_id" jdbcType="INTEGER" property="userId" />
    <result column="group_id" jdbcType="INTEGER" property="groupId" />
    <result column="page_view" jdbcType="INTEGER" property="pageView" />
    <result column="create_time" jdbcType="TIMESTAMP" property="createTime" />
    <result column="create_user" jdbcType="VARCHAR" property="createUser" />
    <result column="update_time" jdbcType="TIMESTAMP" property="updateTime" />
    <result column="update_user" jdbcType="VARCHAR" property="updateUser" />
    <result column="delete_flag" jdbcType="BIT" property="deleteFlag" />
  </resultMap>
  <resultMap extends="BaseResultMap" id="ResultMapWithBLOBs" type="com.dl.movieservice.model.GroupsTopic">
    <result column="front_content" jdbcType="LONGVARCHAR" property="frontContent" />
  </resultMap>
  <sql id="Example_Where_Clause">
    <where>
      <foreach collection="oredCriteria" item="criteria" separator="or">
        <if test="criteria.valid">
          <trim prefix="(" prefixOverrides="and" suffix=")">
            <foreach collection="criteria.criteria" item="criterion">
              <choose>
                <when test="criterion.noValue">
                  and ${criterion.condition}
                </when>
                <when test="criterion.singleValue">
                  and ${criterion.condition} #{criterion.value}
                </when>
                <when test="criterion.betweenValue">
                  and ${criterion.condition} #{criterion.value} and #{criterion.secondValue}
                </when>
                <when test="criterion.listValue">
                  and ${criterion.condition}
                  <foreach close=")" collection="criterion.value" item="listItem" open="(" separator=",">
                    #{listItem}
                  </foreach>
                </when>
              </choose>
            </foreach>
          </trim>
        </if>
      </foreach>
    </where>
  </sql>
  <sql id="Update_By_Example_Where_Clause">
    <where>
      <foreach collection="example.oredCriteria" item="criteria" separator="or">
        <if test="criteria.valid">
          <trim prefix="(" prefixOverrides="and" suffix=")">
            <foreach collection="criteria.criteria" item="criterion">
              <choose>
                <when test="criterion.noValue">
                  and ${criterion.condition}
                </when>
                <when test="criterion.singleValue">
                  and ${criterion.condition} #{criterion.value}
                </when>
                <when test="criterion.betweenValue">
                  and ${criterion.condition} #{criterion.value} and #{criterion.secondValue}
                </when>
                <when test="criterion.listValue">
                  and ${criterion.condition}
                  <foreach close=")" collection="criterion.value" item="listItem" open="(" separator=",">
                    #{listItem}
                  </foreach>
                </when>
              </choose>
            </foreach>
          </trim>
        </if>
      </foreach>
    </where>
  </sql>
  <sql id="Base_Column_List">
    id, title, user_id, group_id, page_view, create_time, create_user, update_time, update_user, 
    delete_flag
  </sql>
  <sql id="Blob_Column_List">
    front_content
  </sql>
  <select id="selectByExampleWithBLOBs" parameterType="com.dl.movieservice.model.GroupsTopicExample" resultMap="ResultMapWithBLOBs">
    select
    <if test="distinct">
      distinct
    </if>
    <include refid="Base_Column_List" />
    ,
    <include refid="Blob_Column_List" />
    from groups_topic
    <if test="_parameter != null">
      <include refid="Example_Where_Clause" />
    </if>
    <if test="orderByClause != null">
      order by ${orderByClause}
    </if>
  </select>
  <select id="selectByExample" parameterType="com.dl.movieservice.model.GroupsTopicExample" resultMap="BaseResultMap">
    select
    <if test="distinct">
      distinct
    </if>
    <include refid="Base_Column_List" />
    from groups_topic
    <if test="_parameter != null">
      <include refid="Example_Where_Clause" />
    </if>
    <if test="orderByClause != null">
      order by ${orderByClause}
    </if>
    <if test="limitStart != null and limitStart>=0">
      limit #{limitStart} , #{limitEnd}
    </if>
  </select>
  <select id="selectByPrimaryKey" parameterType="java.lang.Integer" resultMap="ResultMapWithBLOBs">
    select 
    <include refid="Base_Column_List" />
    ,
    <include refid="Blob_Column_List" />
    from groups_topic
    where id = #{id,jdbcType=INTEGER}
  </select>
  <delete id="deleteByPrimaryKey" parameterType="java.lang.Integer">
    delete from groups_topic
    where id = #{id,jdbcType=INTEGER}
  </delete>
  <delete id="deleteByExample" parameterType="com.dl.movieservice.model.GroupsTopicExample">
    delete from groups_topic
    <if test="_parameter != null">
      <include refid="Example_Where_Clause" />
    </if>
  </delete>
  <insert id="insert" parameterType="com.dl.movieservice.model.GroupsTopic">
    <selectKey keyProperty="id" order="AFTER" resultType="java.lang.Integer">
      SELECT LAST_INSERT_ID()
    </selectKey>
    insert into groups_topic (title, user_id, group_id, 
      page_view, create_time, create_user, 
      update_time, update_user, delete_flag, 
      front_content)
    values (#{title,jdbcType=VARCHAR}, #{userId,jdbcType=INTEGER}, #{groupId,jdbcType=INTEGER}, 
      #{pageView,jdbcType=INTEGER}, #{createTime,jdbcType=TIMESTAMP}, #{createUser,jdbcType=VARCHAR}, 
      #{updateTime,jdbcType=TIMESTAMP}, #{updateUser,jdbcType=VARCHAR}, #{deleteFlag,jdbcType=BIT}, 
      #{frontContent,jdbcType=LONGVARCHAR})
  </insert>
  <insert id="insertSelective" parameterType="com.dl.movieservice.model.GroupsTopic">
    <selectKey keyProperty="id" order="AFTER" resultType="java.lang.Integer">
      SELECT LAST_INSERT_ID()
    </selectKey>
    insert into groups_topic
    <trim prefix="(" suffix=")" suffixOverrides=",">
      <if test="title != null">
        title,
      </if>
      <if test="userId != null">
        user_id,
      </if>
      <if test="groupId != null">
        group_id,
      </if>
      <if test="pageView != null">
        page_view,
      </if>
      <if test="createTime != null">
        create_time,
      </if>
      <if test="createUser != null">
        create_user,
      </if>
      <if test="updateTime != null">
        update_time,
      </if>
      <if test="updateUser != null">
        update_user,
      </if>
      <if test="deleteFlag != null">
        delete_flag,
      </if>
      <if test="frontContent != null">
        front_content,
      </if>
    </trim>
    <trim prefix="values (" suffix=")" suffixOverrides=",">
      <if test="title != null">
        #{title,jdbcType=VARCHAR},
      </if>
      <if test="userId != null">
        #{userId,jdbcType=INTEGER},
      </if>
      <if test="groupId != null">
        #{groupId,jdbcType=INTEGER},
      </if>
      <if test="pageView != null">
        #{pageView,jdbcType=INTEGER},
      </if>
      <if test="createTime != null">
        #{createTime,jdbcType=TIMESTAMP},
      </if>
      <if test="createUser != null">
        #{createUser,jdbcType=VARCHAR},
      </if>
      <if test="updateTime != null">
        #{updateTime,jdbcType=TIMESTAMP},
      </if>
      <if test="updateUser != null">
        #{updateUser,jdbcType=VARCHAR},
      </if>
      <if test="deleteFlag != null">
        #{deleteFlag,jdbcType=BIT},
      </if>
      <if test="frontContent != null">
        #{frontContent,jdbcType=LONGVARCHAR},
      </if>
    </trim>
  </insert>
  <select id="countByExample" parameterType="com.dl.movieservice.model.GroupsTopicExample" resultType="java.lang.Long">
    select count(*) from groups_topic
    <if test="_parameter != null">
      <include refid="Example_Where_Clause" />
    </if>
  </select>
  <update id="updateByExampleSelective" parameterType="map">
    update groups_topic
    <set>
      <if test="record.id != null">
        id = #{record.id,jdbcType=INTEGER},
      </if>
      <if test="record.title != null">
        title = #{record.title,jdbcType=VARCHAR},
      </if>
      <if test="record.userId != null">
        user_id = #{record.userId,jdbcType=INTEGER},
      </if>
      <if test="record.groupId != null">
        group_id = #{record.groupId,jdbcType=INTEGER},
      </if>
      <if test="record.pageView != null">
        page_view = #{record.pageView,jdbcType=INTEGER},
      </if>
      <if test="record.createTime != null">
        create_time = #{record.createTime,jdbcType=TIMESTAMP},
      </if>
      <if test="record.createUser != null">
        create_user = #{record.createUser,jdbcType=VARCHAR},
      </if>
      <if test="record.updateTime != null">
        update_time = #{record.updateTime,jdbcType=TIMESTAMP},
      </if>
      <if test="record.updateUser != null">
        update_user = #{record.updateUser,jdbcType=VARCHAR},
      </if>
      <if test="record.deleteFlag != null">
        delete_flag = #{record.deleteFlag,jdbcType=BIT},
      </if>
      <if test="record.frontContent != null">
        front_content = #{record.frontContent,jdbcType=LONGVARCHAR},
      </if>
    </set>
    <if test="_parameter != null">
      <include refid="Update_By_Example_Where_Clause" />
    </if>
  </update>
  <update id="updateByExampleWithBLOBs" parameterType="map">
    update groups_topic
    set id = #{record.id,jdbcType=INTEGER},
      title = #{record.title,jdbcType=VARCHAR},
      user_id = #{record.userId,jdbcType=INTEGER},
      group_id = #{record.groupId,jdbcType=INTEGER},
      page_view = #{record.pageView,jdbcType=INTEGER},
      create_time = #{record.createTime,jdbcType=TIMESTAMP},
      create_user = #{record.createUser,jdbcType=VARCHAR},
      update_time = #{record.updateTime,jdbcType=TIMESTAMP},
      update_user = #{record.updateUser,jdbcType=VARCHAR},
      delete_flag = #{record.deleteFlag,jdbcType=BIT},
      front_content = #{record.frontContent,jdbcType=LONGVARCHAR}
    <if test="_parameter != null">
      <include refid="Update_By_Example_Where_Clause" />
    </if>
  </update>
  <update id="updateByExample" parameterType="map">
    update groups_topic
    set id = #{record.id,jdbcType=INTEGER},
      title = #{record.title,jdbcType=VARCHAR},
      user_id = #{record.userId,jdbcType=INTEGER},
      group_id = #{record.groupId,jdbcType=INTEGER},
      page_view = #{record.pageView,jdbcType=INTEGER},
      create_time = #{record.createTime,jdbcType=TIMESTAMP},
      create_user = #{record.createUser,jdbcType=VARCHAR},
      update_time = #{record.updateTime,jdbcType=TIMESTAMP},
      update_user = #{record.updateUser,jdbcType=VARCHAR},
      delete_flag = #{record.deleteFlag,jdbcType=BIT}
    <if test="_parameter != null">
      <include refid="Update_By_Example_Where_Clause" />
    </if>
  </update>
  <update id="updateByPrimaryKeySelective" parameterType="com.dl.movieservice.model.GroupsTopic">
    update groups_topic
    <set>
      <if test="title != null">
        title = #{title,jdbcType=VARCHAR},
      </if>
      <if test="userId != null">
        user_id = #{userId,jdbcType=INTEGER},
      </if>
      <if test="groupId != null">
        group_id = #{groupId,jdbcType=INTEGER},
      </if>
      <if test="pageView != null">
        page_view = #{pageView,jdbcType=INTEGER},
      </if>
      <if test="createTime != null">
        create_time = #{createTime,jdbcType=TIMESTAMP},
      </if>
      <if test="createUser != null">
        create_user = #{createUser,jdbcType=VARCHAR},
      </if>
      <if test="updateTime != null">
        update_time = #{updateTime,jdbcType=TIMESTAMP},
      </if>
      <if test="updateUser != null">
        update_user = #{updateUser,jdbcType=VARCHAR},
      </if>
      <if test="deleteFlag != null">
        delete_flag = #{deleteFlag,jdbcType=BIT},
      </if>
      <if test="frontContent != null">
        front_content = #{frontContent,jdbcType=LONGVARCHAR},
      </if>
    </set>
    where id = #{id,jdbcType=INTEGER}
  </update>
  <update id="updateByPrimaryKeyWithBLOBs" parameterType="com.dl.movieservice.model.GroupsTopic">
    update groups_topic
    set title = #{title,jdbcType=VARCHAR},
      user_id = #{userId,jdbcType=INTEGER},
      group_id = #{groupId,jdbcType=INTEGER},
      page_view = #{pageView,jdbcType=INTEGER},
      create_time = #{createTime,jdbcType=TIMESTAMP},
      create_user = #{createUser,jdbcType=VARCHAR},
      update_time = #{updateTime,jdbcType=TIMESTAMP},
      update_user = #{updateUser,jdbcType=VARCHAR},
      delete_flag = #{deleteFlag,jdbcType=BIT},
      front_content = #{frontContent,jdbcType=LONGVARCHAR}
    where id = #{id,jdbcType=INTEGER}
  </update>
  <update id="updateByPrimaryKey" parameterType="com.dl.movieservice.model.GroupsTopic">
    update groups_topic
    set title = #{title,jdbcType=VARCHAR},
      user_id = #{userId,jdbcType=INTEGER},
      group_id = #{groupId,jdbcType=INTEGER},
      page_view = #{pageView,jdbcType=INTEGER},
      create_time = #{createTime,jdbcType=TIMESTAMP},
      create_user = #{createUser,jdbcType=VARCHAR},
      update_time = #{updateTime,jdbcType=TIMESTAMP},
      update_user = #{updateUser,jdbcType=VARCHAR},
      delete_flag = #{deleteFlag,jdbcType=BIT}
    where id = #{id,jdbcType=INTEGER}
  </update>
</mapper>